LICENSE
MANIFEST.in
README.md
setup.py
restapisdk/__init__.py
restapisdk/api_helper.py
restapisdk/configuration.py
restapisdk/decorators.py
restapisdk/restapisdk_client.py
restapisdk/controllers/__init__.py
restapisdk/controllers/admin_controller.py
restapisdk/controllers/base_controller.py
restapisdk/controllers/connection_controller.py
restapisdk/controllers/custom_actions_controller.py
restapisdk/controllers/data_controller.py
restapisdk/controllers/database_controller.py
restapisdk/controllers/group_controller.py
restapisdk/controllers/logs_controller.py
restapisdk/controllers/materialization_controller.py
restapisdk/controllers/metadata_controller.py
restapisdk/controllers/report_controller.py
restapisdk/controllers/security_controller.py
restapisdk/controllers/session_controller.py
restapisdk/controllers/user_controller.py
restapisdk/exceptions/__init__.py
restapisdk/exceptions/api_exception.py
restapisdk/exceptions/error_response_exception.py
restapisdk/http/__init__.py
restapisdk/http/http_call_back.py
restapisdk/http/http_client.py
restapisdk/http/http_method_enum.py
restapisdk/http/http_request.py
restapisdk/http/http_response.py
restapisdk/http/requests_client.py
restapisdk/http/auth/__init__.py
restapisdk/http/auth/o_auth_2.py
restapisdk/models/__init__.py
restapisdk/models/access_level_input.py
restapisdk/models/access_level_input_access_enum.py
restapisdk/models/access_level_input_type_enum.py
restapisdk/models/add_privileges_to_group_privileges_enum.py
restapisdk/models/add_table_input.py
restapisdk/models/adminsync_principal_response.py
restapisdk/models/answer_data_format_type_enum.py
restapisdk/models/answer_query_response.py
restapisdk/models/answer_report_type_enum.py
restapisdk/models/client_state.py
restapisdk/models/columns_input.py
restapisdk/models/connection_column.py
restapisdk/models/connection_columns_shema.py
restapisdk/models/connection_database_type.py
restapisdk/models/connection_response.py
thoughtspot_rest_api_sdk.egg-info/PKG-INFO
thoughtspot_rest_api_sdk.egg-info/SOURCES.txt
thoughtspot_rest_api_sdk.egg-info/dependency_links.txt
thoughtspot_rest_api_sdk.egg-info/requires.txt
thoughtspot_rest_api_sdk.egg-info/top_level.txt