Metadata-Version: 2.1
Name: thoughtspot-rest-api-sdk
Version: 1.11.0
Summary: Python client library for RESTAPI SDK
Home-page: https://github.com/thoughtspot/rest-api-sdk/tree/1.11.0/Python
Author: ThoughtSpot
Author-email: support@thoughtspot.com
License: UNKNOWN
Platform: UNKNOWN
License-File: LICENSE
